extrakit_cli/__init__.py
extrakit_cli/sample_int.py
extrakit_cli-0.1.0.dist-info/WHEEL
extrakit_cli-0.1.0.dist-info/entry_points.txt
extrakit_cli-0.1.0.dist-info/METADATA
extrakit_cli-0.1.0.dist-info/RECORD
